alphaimpute2/alphaimpute2.py
alphaimpute2/Imputation/ArrayClustering.py
alphaimpute2/Imputation/BurrowsWheelerLibrary.py
alphaimpute2/Imputation/Heuristic_Peeling.py
alphaimpute2/Imputation/Imputation.py
alphaimpute2/Imputation/ImputationIndividual.py
alphaimpute2/Imputation/ParticleImputation.py
alphaimpute2/Imputation/ParticlePhasing.py
alphaimpute2/Imputation/PhasingObjects.py
alphaimpute2/Imputation/version.py
alphaimpute2/tinyhouse/BurrowsWheelerLibrary.py
alphaimpute2/tinyhouse/CombinedHMM.py
alphaimpute2/tinyhouse/DiploidHMM.py
alphaimpute2/tinyhouse/HaploidHMM.py
alphaimpute2/tinyhouse/HaplotypeLibrary.py
alphaimpute2/tinyhouse/HaplotypeOperations.py
alphaimpute2/tinyhouse/InputOutput.py
alphaimpute2/tinyhouse/MultiThreadIO.py
alphaimpute2/tinyhouse/NumbaUtils.py
alphaimpute2/tinyhouse/Pedigree.py
alphaimpute2/tinyhouse/ProbMath.py
alphaimpute2/tinyhouse/Utils.py
alphaimpute2-0.0.3.dist-info/METADATA
alphaimpute2-0.0.3.dist-info/WHEEL
alphaimpute2-0.0.3.dist-info/entry_points.txt
alphaimpute2-0.0.3.dist-info/top_level.txt
alphaimpute2-0.0.3.dist-info/RECORD
