Metadata-Version: 2.4
Name: AlphaImpute2
Version: 0.0.3
Summary: An imputation software for massive livestock populations.
Author-email: Andrew Whalen <awhalen@roslin.ed.ac.uk>
License-Expression: MIT
Project-URL: Homepage, https://github.com/AlphaGenes/AlphaImpute2
Project-URL: Bug Tracker, https://github.com/AlphaGenes/AlphaImpute2/issues
Classifier: Programming Language :: Python :: 3
Requires-Python: !=3.12,!=3.14
Requires-Dist: numpy>=1.19
Requires-Dist: numba>=0.49.0
